fastrtc_canary/__init__.py
fastrtc_canary/model.py
fastrtc_canary/test_file.wav
fastrtc_canary/utils.py
fastrtc_canary-0.0.2.dist-info/METADATA
fastrtc_canary-0.0.2.dist-info/WHEEL
fastrtc_canary-0.0.2.dist-info/licenses/LICENSE
fastrtc_canary-0.0.2.dist-info/RECORD
