Metadata-Version: 2.4
Name: fastrtc_canary
Version: 0.0.2
Summary: The realtime communication library for Python - fastrtc with Nvidia's Canary STT
Project-URL: repository, https://github.com/freddyaboulton/gradio-webrtc
Project-URL: issues, https://github.com/freddyaboulton/gradio-webrtc/issues
Project-URL: Documentation, https://freddyaboulton.github.io/gradio-webrtc/cookbook/
Author-email: Freddy Boulton <YOUREMAIL@domain.com>, Mahimai Raja <YOUREMAIL@domain.com>
License-Expression: Apache-2.0
License-File: LICENSE
Keywords: audio,audio processing,computer vision,gradio-custom-component,image,machine learning,realtime,streaming,video,video processing,webrtc
Classifier: Development Status :: 3 - Alpha
Classifier: Operating System :: OS Independent
Classifier: Programming Language :: Python :: 3
Classifier: Programming Language :: Python :: 3 :: Only
Classifier: Programming Language :: Python :: 3.10
Classifier: Programming Language :: Python :: 3.11
Classifier: Programming Language :: Python :: 3.12
Classifier: Programming Language :: Python :: 3.13
Classifier: Topic :: Internet
Classifier: Topic :: Scientific/Engineering
Classifier: Topic :: Scientific/Engineering :: Artificial Intelligence
Classifier: Topic :: Scientific/Engineering :: Visualization
Classifier: Topic :: Software Development
Classifier: Topic :: Software Development :: Libraries
Classifier: Topic :: Software Development :: Libraries :: Application Frameworks
Classifier: Topic :: Software Development :: Libraries :: Python Modules
Requires-Python: >=3.10
Requires-Dist: aiortc
Requires-Dist: audioop-lts; python_version >= '3.13'
Requires-Dist: librosa
Requires-Dist: nemo-toolkit[asr]
Requires-Dist: numba>=0.60.0
Requires-Dist: numpy>=2.0.2
Requires-Dist: standard-aifc; python_version >= '3.13'
Requires-Dist: standard-sunau; python_version >= '3.13'
Provides-Extra: dev
Requires-Dist: build; extra == 'dev'
Requires-Dist: twine; extra == 'dev'
